snspotting/__init__.py
snspotting-0.0.1.dist-info/LICENSE
snspotting-0.0.1.dist-info/METADATA
snspotting-0.0.1.dist-info/WHEEL
snspotting-0.0.1.dist-info/top_level.txt
snspotting-0.0.1.dist-info/RECORD
